{
	"balanced_sampling": false,
	"batch_size": 32,
	"case_sensitive": false,
	"characters": " abcdefghijklmnopqrstuvwxyzçèéßäöōǎǐíǒàáǔüèéìūòóùúāēěīâêôûñőűабвгдежзийклмнопрстуфхцчшщъыьэюяёάέήίαβγδεζηθικλμνξοπρςíστυφχψωόύώ",
	"checkpoint_each_epochs": 5,
    "use_phonemes": false,
	"dataset": "css10",
	"encoder_type": "simple",
	"epochs": 100,
	"languages": ["german", "dutch", "chinese", "japanese"],
	"language_embedding_dimension": 4,
	"learning_rate": 0.001,
    "learning_rate_decay_each": 9999,
	"multi_language": true,
    "one_hot_lang_emb": true,
    "perfect_sampling": false,
	"predict_linear": false,
    "sort_by_text_len": true,
    "use_ewc": false,
    "ewc_sample_size": 2048,
    "ewc_importance": 1.0,
    "use_kd": false,
    "kd_stop_token": true,
    "kd_attention": true,
    "kd_importance": 0.5,
    "use_replay": false,
    "basic_imbalance_sampling": false,
    "aux_imbalance_sampling": false,
    "rrs_importance": 1.0,
    "cbs_importance": 0.5,
    "unique_postnet": false,
    "use_gem": false,
    "memory_strength": 0.5,
    "replay_size": 300,
    "training_file": "train_ge+ch+ja+du.txt",
    "validation_file": "val_ge+ch+ja+du.txt",
	"version": "SHARED-TRAINING"
}
